datehelper/__init__.py
datehelper/core.py
tests/__init__.py
tests/test_datehelper.py
datehelper_now_youre_unemployed-0.1.6.dist-info/LICENSE
datehelper_now_youre_unemployed-0.1.6.dist-info/METADATA
datehelper_now_youre_unemployed-0.1.6.dist-info/WHEEL
datehelper_now_youre_unemployed-0.1.6.dist-info/top_level.txt
datehelper_now_youre_unemployed-0.1.6.dist-info/RECORD
