Metadata-Version: 2.1
Name: datehelper-now_youre_unemployed
Version: 0.1.6
Summary: A simple date helper library.
Author: now-youre-unemployed
Requires-Python: >=3.6
License-File: LICENSE
